speech_patho_mdl/__init__.py
speech_patho_mdl/__init__.pyi
speech_patho_mdl/bp/__init__.py
speech_patho_mdl/bp/__init__.pyi
speech_patho_mdl/bp/model_api.py
speech_patho_mdl/bp/model_api.pyi
speech_patho_mdl/bp.pyi
speech_patho_mdl/dmo/__init__.py
speech_patho_mdl/dmo/__init__.pyi
speech_patho_mdl/dmo/custom_openai_pathology.py
speech_patho_mdl/dmo/custom_openai_pathology.pyi
speech_patho_mdl/dmo/custom_openai_speechdisorder.py
speech_patho_mdl/dmo/custom_openai_speechdisorder.pyi
speech_patho_mdl/dmo/model_config_loader.py
speech_patho_mdl/dmo/model_config_loader.pyi
speech_patho_mdl/dmo/random_pathology_question.py
speech_patho_mdl/dmo/random_pathology_question.pyi
speech_patho_mdl/dmo/random_speechdisorder_question.py
speech_patho_mdl/dmo/random_speechdisorder_question.pyi
speech_patho_mdl/dmo.pyi
speech_patho_mdl/dto/__init__.py
speech_patho_mdl/dto/__init__.pyi
speech_patho_mdl/dto/classification_schema_kb.py
speech_patho_mdl/dto/classification_schema_kb.pyi
speech_patho_mdl/dto/model_type_hints_kb.py
speech_patho_mdl/dto/model_type_hints_kb.pyi
speech_patho_mdl/dto/models_kb.py
speech_patho_mdl/dto/models_kb.pyi
speech_patho_mdl/dto/praxis_pathology_kb.py
speech_patho_mdl/dto/praxis_pathology_kb.pyi
speech_patho_mdl/dto/speech_disorder_kb.py
speech_patho_mdl/dto/speech_disorder_kb.pyi
speech_patho_mdl/dto/typedefs.py
speech_patho_mdl/dto/typedefs.pyi
speech_patho_mdl/dto.pyi
speech_patho_mdl/svc/__init__.py
speech_patho_mdl/svc/__init__.pyi
speech_patho_mdl/svc/classify_input_tags.py
speech_patho_mdl/svc/classify_input_tags.pyi
speech_patho_mdl/svc/initialize_named_model.py
speech_patho_mdl/svc/initialize_named_model.pyi
speech_patho_mdl/svc/invoke_named_model.py
speech_patho_mdl/svc/invoke_named_model.pyi
speech_patho_mdl/svc.pyi
speech_patho_mdl-0.1.4.dist-info/WHEEL
speech_patho_mdl-0.1.4.dist-info/METADATA
speech_patho_mdl-0.1.4.dist-info/RECORD
