Metadata-Version: 2.1
Name: speech-patho-mdl
Version: 0.1.4
Summary: Custom Trained Models for Speech Pathology
Home-page: https://github.com/craigtrim/speech-patho-mdl
License: MIT
Keywords: nlp,nlu,ai,classification,intents
Author: Craig Trim
Author-email: craigtrim@gmail.com
Maintainer: Craig Trim
Maintainer-email: craigtrim@gmail.com
Requires-Python: ==3.8.5
Classifier: Development Status :: 4 - Beta
Classifier: License :: OSI Approved :: MIT License
Classifier: Programming Language :: Python :: 3
Classifier: Topic :: Scientific/Engineering :: Artificial Intelligence
Classifier: Topic :: Software Development :: Libraries :: Python Modules
Requires-Dist: baseblock
Requires-Dist: boto3
Requires-Dist: openai (>=0.20.0,<0.21.0)
Requires-Dist: openai-helper
Requires-Dist: opensearch-helper
Requires-Dist: opensearch-py (>=1.1.0,<2.0.0)
Requires-Dist: owl-builder
Requires-Dist: owl-parser
Requires-Dist: requests
Requires-Dist: schema-classification
Project-URL: Repository, https://github.com/craigtrim/speech-patho-mdl
